proctor/__init__.py
proctor/base.py
proctor/config.py
proctor/utils.py
proctor/decomposition/__init__.py
proctor/decomposition/techniques.py
proctor/ensembling/__init__.py
proctor/ensembling/techniques.py
proctor/few_shot/__init__.py
proctor/few_shot/knn_implementation.py
proctor/few_shot/techniques.py
proctor/self_criticism/__init__.py
proctor/self_criticism/techniques.py
proctor/thought_generation/__init__.py
proctor/thought_generation/techniques.py
proctor/zero_shot/__init__.py
proctor/zero_shot/techniques.py
proctor_ai-0.1.2.dist-info/licenses/LICENSE
proctor_ai-0.1.2.dist-info/METADATA
proctor_ai-0.1.2.dist-info/WHEEL
proctor_ai-0.1.2.dist-info/top_level.txt
proctor_ai-0.1.2.dist-info/RECORD
