Metadata-Version: 2.4
Name: proctor-ai
Version: 0.1.2
Summary: A comprehensive Python package for structured prompt engineering techniques
Home-page: https://github.com/svngoku/proctor
Author: Your Name
Author-email: Svngoku <svngokuofficiel@gmail.com>
License: MIT
Project-URL: Homepage, https://github.com/svngoku/proctor
Project-URL: Bug Tracker, https://github.com/svngoku/proctor/issues
Project-URL: Documentation, https://github.com/svngoku/proctor/blob/master/README.md
Project-URL: Source Code, https://github.com/svngoku/proctor
Keywords: prompt-engineering,llm,ai,nlp,gpt,openai,prompt-templates
Classifier: Development Status :: 4 - Beta
Classifier: Intended Audience :: Developers
Classifier: Intended Audience :: Science/Research
Classifier: License :: OSI Approved :: MIT License
Classifier: Programming Language :: Python :: 3
Classifier: Programming Language :: Python :: 3.8
Classifier: Programming Language :: Python :: 3.9
Classifier: Programming Language :: Python :: 3.10
Classifier: Programming Language :: Python :: 3.11
Classifier: Topic :: Scientific/Engineering :: Artificial Intelligence
Classifier: Operating System :: OS Independent
Requires-Python: >=3.8
License-File: LICENSE
Requires-Dist: build>=1.2.2.post1
Requires-Dist: litellm>=1.0.0
Requires-Dist: openai>=1.0.0
Requires-Dist: python-dotenv>=0.20.0
Requires-Dist: rich>=13.0.0
Requires-Dist: twine>=6.1.0
Requires-Dist: aiohttp>=3.9.0
Provides-Extra: knn
Requires-Dist: sentence-transformers>=2.0.0; extra == "knn"
Requires-Dist: scikit-learn>=1.0.0; extra == "knn"
Provides-Extra: dev
Requires-Dist: pytest>=7.0.0; extra == "dev"
Requires-Dist: pytest-cov>=4.0.0; extra == "dev"
Requires-Dist: ruff>=0.0.270; extra == "dev"
Requires-Dist: build>=0.10.0; extra == "dev"
Provides-Extra: all
Requires-Dist: sentence-transformers>=2.0.0; extra == "all"
Requires-Dist: scikit-learn>=1.0.0; extra == "all"
Requires-Dist: pytest>=7.0.0; extra == "all"
Requires-Dist: pytest-cov>=4.0.0; extra == "all"
Requires-Dist: ruff>=0.0.270; extra == "all"
Requires-Dist: build>=0.10.0; extra == "all"
Dynamic: author
Dynamic: home-page
Dynamic: license-file
Dynamic: requires-python
